COPYING.txt
MANIFEST.in
README.rst
requirements.txt
setup.py
IntDump.egg-info/PKG-INFO
IntDump.egg-info/SOURCES.txt
IntDump.egg-info/dependency_links.txt
IntDump.egg-info/entry_points.txt
IntDump.egg-info/requires.txt
IntDump.egg-info/top_level.txt
intdump/__init__.py
intdump/interpreters.py
intdump/main.py
intdump/version.txt