Metadata-Version: 1.1
Name: IntDump
Version: 0.1.1
Summary: Interpret binary files in some predefined manners.
Home-page: https://github.com/NoviceLive/intdump
Author: Gu Zhengxiong
Author-email: rectigu@gmail.com
License: GPL-3
Keywords: Binary File,Data Interpretation,Integer Dumping
Platform: UNKNOWN
Classifier: Development Status :: 4 - Beta
Classifier: License :: OSI Approved :: GNU General Public License v3 or later (GPLv3+)
Classifier: Programming Language :: Python :: 3.2
